perspective/__init__.py
perspective/api_client.py
perspective/attribute_types.py
perspective/languages.py
perspective/perspective.py
perspective/validators.py
perspective-1.0.3.dist-info/LICENSE.txt
perspective-1.0.3.dist-info/METADATA
perspective-1.0.3.dist-info/WHEEL
perspective-1.0.3.dist-info/top_level.txt
perspective-1.0.3.dist-info/RECORD
