Metadata-Version: 2.1
Name: perspective
Version: 1.0.3
Summary: A package for interacting with the Perspective API
Home-page: https://github.com/conway/perspective
Author: Jake Conway
Author-email: jake.h.conway@gmail.com
License: UNKNOWN
Project-URL: Bug Tracker, https://github.com/conway/perspective/issues
Platform: UNKNOWN
Classifier: Programming Language :: Python :: 3
Classifier: License :: OSI Approved :: MIT License
Classifier: Operating System :: OS Independent
Requires-Python: >=3.8
